checkbin/__about__.py
checkbin/__init__.py
checkbin/cli.py
checkbin/local.py
checkbin/server.py
checkbin/utils.py
checkbin-0.0.7.dist-info/METADATA
checkbin-0.0.7.dist-info/WHEEL
checkbin-0.0.7.dist-info/entry_points.txt
checkbin-0.0.7.dist-info/licenses/LICENSE.txt
checkbin-0.0.7.dist-info/RECORD
