Metadata-Version: 2.4
Name: checkbin
Version: 0.0.7
Summary: Visualization SDK
Project-URL: Documentation, https://github.com/checkbins/checkbin-python#readme
Project-URL: Issues, https://github.com/checkbins/checkbin-python/issues
Project-URL: Source, https://github.com/checkbins/checkbin-python
Author-email: Jay Swanson <jay@synth.inc>
License-Expression: MIT
License-File: LICENSE.txt
Classifier: Development Status :: 4 - Beta
Classifier: Programming Language :: Python
Classifier: Programming Language :: Python :: 3.8
Classifier: Programming Language :: Python :: 3.9
Classifier: Programming Language :: Python :: 3.10
Classifier: Programming Language :: Python :: 3.11
Classifier: Programming Language :: Python :: 3.12
Classifier: Programming Language :: Python :: Implementation :: CPython
Classifier: Programming Language :: Python :: Implementation :: PyPy
Requires-Python: >=3.8
Requires-Dist: azure-storage-blob
Requires-Dist: azure-storage-file-datalake
Requires-Dist: boto3
Requires-Dist: fastapi
Requires-Dist: google-cloud-storage
Requires-Dist: numpy
Requires-Dist: opencv-python
Requires-Dist: requests
Requires-Dist: tinydb
Requires-Dist: torch
